odoo/addons/sale_automatic_workflow_periodicity/README.rst
odoo/addons/sale_automatic_workflow_periodicity/__init__.py
odoo/addons/sale_automatic_workflow_periodicity/__manifest__.py
odoo/addons/sale_automatic_workflow_periodicity/i18n/es.po
odoo/addons/sale_automatic_workflow_periodicity/i18n/it.po
odoo/addons/sale_automatic_workflow_periodicity/i18n/sale_automatic_workflow_periodicity.pot
odoo/addons/sale_automatic_workflow_periodicity/models/__init__.py
odoo/addons/sale_automatic_workflow_periodicity/models/automatic_workflow_job.py
odoo/addons/sale_automatic_workflow_periodicity/models/sale_workflow_process.py
odoo/addons/sale_automatic_workflow_periodicity/readme/CONTRIBUTORS.md
odoo/addons/sale_automatic_workflow_periodicity/readme/CREDITS.md
odoo/addons/sale_automatic_workflow_periodicity/readme/DESCRIPTION.md
odoo/addons/sale_automatic_workflow_periodicity/static/description/icon.png
odoo/addons/sale_automatic_workflow_periodicity/static/description/index.html
odoo/addons/sale_automatic_workflow_periodicity/tests/__init__.py
odoo/addons/sale_automatic_workflow_periodicity/tests/test_auto_workflow_periodicity.py
odoo/addons/sale_automatic_workflow_periodicity/views/sale_workflow_process_view.xml
odoo_addon_sale_automatic_workflow_periodicity-18.0.1.0.0.5.dist-info/METADATA
odoo_addon_sale_automatic_workflow_periodicity-18.0.1.0.0.5.dist-info/WHEEL
odoo_addon_sale_automatic_workflow_periodicity-18.0.1.0.0.5.dist-info/top_level.txt
odoo_addon_sale_automatic_workflow_periodicity-18.0.1.0.0.5.dist-info/RECORD
