Metadata-Version: 2.1
Name: odoo-addon-sale_automatic_workflow_periodicity
Version: 18.0.1.0.0.5
Requires-Python: >=3.10
Requires-Dist: odoo-addon-sale_automatic_workflow==18.0.*
Requires-Dist: odoo==18.0.*
Summary: Adds a period for the execution of a workflow.
Home-page: https://github.com/OCA/sale-workflow
License: AGPL-3
Author: Camptocamp, Odoo Community Association (OCA)
Author-email: support@odoo-community.org
Classifier: Programming Language :: Python
Classifier: Framework :: Odoo
Classifier: Framework :: Odoo :: 18.0
Classifier: License :: OSI Approved :: GNU Affero General Public License v3
